[
    {
        "objects": [
            {
                "dynamicString": "return TurnTable{description=\"\", noCollisions=true, modelid=2099, isRandomModelId=false, interior=1, position=Vector3(-0.294921875,1.6622314453125,-0.89312744140625), rotation=Vector3(0,0,0), posOffset=Vector3(0,0,0), rotOffset=Vector3(0,0,0)}",
                "id": 7
            }
        ],
        "poi": {
            "isEmpty": true
        },
        "locations": [
            {
                "Description": "near turntable",
                "Interior": 1,
                "Y": 0.404296875,
                "X": -0.2236328125,
                "episodeLinks": [],
                "Z": 0,
                "id": 7,
                "Angle": 359.9065856933594,
                "PossibleActions": [
                    {
                        "id": 1
                    }
                ],
                "allActions": [
                    {
                        "dynamicString": "return TurnOn{}",
                        "isClosingAction": false,
                        "targetItem": {
                            "id": 7,
                            "type": "Object"
                        },
                        "id": 1,
                        "nextAction": {
                            "id": 2
                        },
                        "closingAction": {
                            "id": 3
                        },
                        "nextLocation": {
                            "id": 7
                        }
                    },
                    {
                        "dynamicString": "return Dance{}",
                        "isClosingAction": false,
                        "targetItem": {
                            "id": -1,
                            "type": "none"
                        },
                        "id": 2,
                        "nextAction": {
                            "id": 3
                        },
                        "nextLocation": {
                            "id": 7
                        }
                    },
                    {
                        "dynamicString": "return TurnOff{}",
                        "isClosingAction": true,
                        "targetItem": {
                            "id": 7,
                            "type": "Object"
                        },
                        "id": 3,
                        "nextLocation": {
                            "id": 7
                        }
                    }
                ]
            }
        ],
        "position": {
            "y": -1673.21240234375,
            "x": 2530.4931640625,
            "z": 1015.498596191406
        },
        "globalCentroid": {
            "y": -1672.17919921875,
            "x": 2530.23388671875,
            "z": 1015.052001953125
        },
        "name": "turnTable"
    }
]